mcp_foundation/__init__.py
mcp_foundation/client/__init__.py
mcp_foundation/client/base.py
mcp_foundation/client/stdio.py
mcp_foundation/client/streamable_http.py
mcp_foundation/components/base_component.py
mcp_foundation/components/cache/__init__.py
mcp_foundation/components/cache/cache.py
mcp_foundation/components/event/README.md
mcp_foundation/components/event/__init__.py
mcp_foundation/components/event/event.py
mcp_foundation/components/logging/__init__.py
mcp_foundation/components/logging/logging.py
mcp_foundation/components/monitoring/README.md
mcp_foundation/components/monitoring/__init__.py
mcp_foundation/components/monitoring/monitoring.py
mcp_foundation/components/security/README.md
mcp_foundation/components/security/__init__.py
mcp_foundation/components/security/security.py
mcp_foundation/config/base.py
mcp_foundation/config/cache.py
mcp_foundation/config/event.py
mcp_foundation/config/logging.py
mcp_foundation/config/monitoring.py
mcp_foundation/config/security.py
mcp_foundation/config/server.py
mcp_foundation/server/context.py
mcp_foundation/server/mcp_server.py
mcp_foundation-0.0.1.dist-info/licenses/LICENSE
mcp_foundation-0.0.1.dist-info/METADATA
mcp_foundation-0.0.1.dist-info/WHEEL
mcp_foundation-0.0.1.dist-info/entry_points.txt
mcp_foundation-0.0.1.dist-info/top_level.txt
mcp_foundation-0.0.1.dist-info/RECORD
