Metadata-Version: 2.4
Name: mcp-foundation
Version: 0.0.1
Summary: Foundation library for building Model Context Protocol (MCP) servers with enterprise features including security, monitoring, caching, and extensible architecture
Author-email: MCP Foundation Team <team@yourcompany.com>
License: MIT
Project-URL: Homepage, https://git.zias.io/tools/mcp-foundation
Project-URL: Repository, https://git.zias.io/tools/mcp-foundation.git
Project-URL: Documentation, https://git.zias.io/tools/mcp-foundation/wiki
Project-URL: Bug Tracker, https://git.zias.io/tools/mcp-foundation/issues
Keywords: mcp,model-context-protocol,ai,framework,library
Classifier: Development Status :: 4 - Beta
Classifier: Intended Audience :: Developers
Classifier: Topic :: Software Development :: Libraries :: Python Modules
Classifier: Topic :: Internet :: WWW/HTTP :: HTTP Servers
Classifier: License :: OSI Approved :: MIT License
Classifier: Programming Language :: Python :: 3
Classifier: Programming Language :: Python :: 3.8
Classifier: Programming Language :: Python :: 3.9
Classifier: Programming Language :: Python :: 3.10
Classifier: Programming Language :: Python :: 3.11
Classifier: Programming Language :: Python :: 3.12
Requires-Python: >=3.8
License-File: LICENSE
Requires-Dist: fastapi>=0.115.0
Requires-Dist: uvicorn>=0.32.0
Requires-Dist: pydantic<3.0.0,>=2.4.2
Requires-Dist: pydantic-settings<3.0.0,>=2.0.3
Requires-Dist: requests<3.0.0,>=2.31.0
Requires-Dist: aiohttp<4.0.0,>=3.8.6
Requires-Dist: croniter<2.0.0,>=1.4.1
Requires-Dist: redis<6.0.0,>=5.0.1
Requires-Dist: paramiko<4.0.0,>=3.3.1
Requires-Dist: PyYAML<7.0.0,>=6.0
Requires-Dist: kafka-python<3.0.0,>=2.0.2
Requires-Dist: fastmcp>=2.11.1
Requires-Dist: jsonschema<5.0.0,>=4.17.0
Requires-Dist: cryptography<5.0.0,>=3.4.8
Requires-Dist: prometheus-client<1.0.0,>=0.16.0
Provides-Extra: dev
Requires-Dist: pytest>=7.0.0; extra == "dev"
Requires-Dist: pytest-asyncio>=0.21.0; extra == "dev"
Requires-Dist: black>=23.0.0; extra == "dev"
Requires-Dist: flake8>=6.0.0; extra == "dev"
Requires-Dist: mypy>=1.0.0; extra == "dev"
Dynamic: license-file
